Project/decoder.v
`timescale 1 ns / 10 ps
module decoder (code,rd_enable,clock, BCD);

output [7:0]BCD;

input [3:0]code;
input rd_enable;
input clock;

reg [7:0]BCD;

always @(posedge clock )
begin
    if (rd_enable) begin
        case (code)
        4'b0000: BCD = 8'b00000000;
        4'b0001: BCD = 8'b00000001;
        4'b0010: BCD = 8'b00000010;
        4'b0011: BCD = 8'b00000011;
        4'b0100: BCD = 8'b00000100;
        4'b0101: BCD = 8'b00000101;
        4'b0110: BCD = 8'b00000110;
        4'b0111: BCD = 8'b00000111;
        4'b1000: BCD = 8'b00001000;
        4'b1001: BCD = 8'b00001001;
        4'b1010: BCD = 8'b00010000;
        4'b1011: BCD = 8'b00010001;
        4'b1100: BCD = 8'b00010010;
        4'b1101: BCD = 8'b00010011;
        4'b1110: BCD = 8'b00010100;
        4'b1111: BCD = 8'b00010101;
    endcase
    end
end

endmodule

Project/decoder_test.v
`timescale 1 ns / 10 ps
module decoder_test();

reg [3:0]code;
reg rd_enable,clock;

wire [7:0]BCD;

decoder d1 (.code(code),.rd_enable(rd_enable),.clock(clock),.BCD(BCD));

initial $monitor("time=%0d rd_enable=%0d BCD=%0h",$time,rd_enable,BCD);

initial
begin
$dumpfile("decoder.vcd");
$dumpvars(0,decoder_test);

clock=1'b0;
forever #5 clock=~clock;
end

initial begin
$display ("%b, %b,", BCD, code);
end

initial begin
rd_enable = 1'd0;
#20 rd_enable = 1'd1;
#10 rd_enable = 1'd0;
#30 rd_enable = 1'd1;
end

initial begin
#20 code = 4'b0010;
#30 code = 4'b1101;
#10 code = 4'b1001;
#10 code = 4'b1011;
#10 code = 4'b1101;
#10 code = 4'b1011;
#10 code = 4'b1101;
end

initial begin
#300 $finish;
end

endmodule

Project/decoder.vcd
$date
	Wed Jul  2 03:30:12 2014
$end

$version
	Synopsys VCS version A-2008.09
$end

$timescale
	10ps
$end

$comment Csum: 1 6e4045d75130a91c $end


$scope module decoder_test $end
$var reg 4 ! code [3:0] $end
$var reg 1 " rd_enable $end
$var reg 1 # clock $end
$var wire 1 $ BCD [7] $end
$var wire 1 % BCD [6] $end
$var wire 1 & BCD [5] $end
$var wire 1 ' BCD [4] $end
$var wire 1 ( BCD [3] $end
$var wire 1 ) BCD [2] $end
$var wire 1 * BCD [1] $end
$var wire 1 + BCD [0] $end

$scope module d1 $end
$var reg 8 , BCD [7:0] $end
$var wire 4 ! code [3:0] $end
$var wire 1 " rd_enable $end
$var wire 1 # clock $end
$upscope $end

$upscope $end

$enddefinitions $end

#0
$dumpvars
x+
x*
x)
x(
x'
x&
x%
x$
0#
0"
bxxxxxxxx ,
bxxxx !
$end
#500
1#
#1000
0#
#1500
1#
#2000
1"
b0010 !
0#
#2500
1#
b00000010 ,
0$
0%
0&
0'
0(
0)
1*
0+
#3000
0"
0#
#3500
1#
#4000
0#
#4500
1#
#5000
b1101 !
0#
#5500
1#
#6000
1"
b1001 !
0#
#6500
1#
b00001001 ,
1(
0*
1+
#7000
b1011 !
0#
#7500
1#
b00010001 ,
1'
0(
#8000
b1101 !
0#
#8500
1#
b00010011 ,
1*
#9000
b1011 !
0#
#9500
1#
b00010001 ,
0*
#10000
b1101 !
0#
#10500
1#
b00010011 ,
1*
