Project/keypad.v
`timescale 1 ns / 10 ps
module keypad(row,col,data,v,clock,reset);
    
output [3:0] col;
output [3:0] data;
output v;

input [3:0] row;
input clock;
input reset;
    

parameter s_0=3'b000,s_1=3'b001,s_2=3'b010,s_3=3'b011,s_4=3'b100,s_5=3'b101;

    reg [2:0] state,	next_state;
    reg [3:0] data;
    reg [3:0] col;
    reg [3:0] store;
    reg v;
	
	
  always@(posedge clock or negedge reset)
  begin
  if (reset == 0) begin state <= s_0;store <= row;end
  else begin	state <= next_state;store <= row; end
  end
	
	always@(posedge clock) begin 
	
	case(state)
	
s_0:if(store==4'b1111) begin next_state = s_0; col<=4'b0000;  v<=0; data<=4'bx; end
    else begin next_state = s_1; col<=col;v<=0;data<=4'bx; end

s_1:if(store==4'b1111) begin next_state = s_2; col<=col;v<=0;data<=data; end
	else begin case(store)
	4'b1110 : begin data <= 4'b0000; v<=1; next_state=s_5;col<=4'b1110; end
	4'b1101 : begin data <= 4'b0100; v<=1; next_state=s_5;col<=4'b1110;end
        4'b1011 : begin data <= 4'b1000; v<=1; next_state=s_5;col<=4'b1110; end
        4'b0111 : begin data <= 4'b1100; v<=1; next_state=s_5;col<=4'b1110; end
        endcase
	end
	
s_2: if(store==4'b1111) begin next_state = s_3; col<=col;v<=0;data<=data; end
	else begin case(store)
        4'b1110 : begin data <= 4'b0001; v<=1; next_state=s_5;col<=4'b1101; end
	4'b1101 : begin data <= 4'b0101; v<=1; next_state=s_5;col<=4'b1101; end
	4'b1011 : begin data <= 4'b1001; v<=1; next_state=s_5;col<=4'b1101; end
	4'b0111 : begin data <= 4'b1101; v<=1; next_state=s_5;col<=4'b1101; end
	endcase
	end
   
s_3: if(store==4'b1111) begin next_state = s_4; col<=col;v<=0;data<=data; end
	else begin case(store)
        4'b1110 : begin data <= 4'b0010; v<=1; next_state=s_5; col<=4'b1011; end
	4'b1101 : begin data <= 4'b0110; v<=1; next_state=s_5; col<=4'b1011; end
        4'b1011 : begin data <= 4'b1010; v<=1; next_state=s_5;col<=4'b1011; end
	4'b0111 : begin data <= 4'b1110; v<=1; next_state=s_5;col<=4'b1011; end
        endcase
	end
  
 s_4: if(store==4'b1111) begin next_state = s_1; col<=col;v<=0;data<=data; end
	 else begin case(store)
         4'b1110 : begin data <= 4'b0011; v<=1; next_state=s_5;col<=4'b0111; end
	 4'b1101 : begin data <= 4'b0111; v<=1; next_state=s_5;col<=4'b0111; end
	 4'b1011 : begin data <= 4'b1011; v<=1; next_state=s_5;col<=4'b0111; end
	 4'b0111 : begin data <= 4'b1111; v<=1; next_state=s_5;col<=4'b0111;end
	 endcase
	 end	
   
s_5: if(store==4'b1111) begin next_state=s_1; col<=col;v<=0;data<=data; end
     else begin next_state=s_5; col <= col; v<=0; data<=data; end

endcase

end		  

endmodule

Project/keypad_test.v
`timescale 1 ns / 10 ps
module keypad_test();

	// Inputs
	reg [3:0] row;
	reg clock;
	reg reset;

	// Outputs
	wire [3:0] col;
	wire [3:0] data;
	wire v;

keypad uut (.row(row),.col(col),.data(data),.v(v),.clock(clock),.reset(reset));

initial $monitor("time=0%d row=0%b col=0%b data=0%h v=0%b reset=0%b",$time,row,col,data,v,reset);

initial begin
$dumpfile("keypad.vcd");
$dumpvars(0,keypad_test);
end

	initial begin
		clock=0;
		reset=0;
		row = 4'b1111;
		#10 reset=1;row=4'b1110;
		#15 row=4'b1111;
		#5 row=4'b1110;
		#20 row=4'b1111;
		#25 row=4'b1110;
		#20 row=4'b1111;
		#35 row=4'b1110;
		#40 row=4'b1111;
		#5 row=4'b1101;
		#25 row=4'b1111;
		#15 row=4'b1101;
		#20 row=4'b1111;
		#25 row=4'b1101;
		#40 row=4'b1111;
		#35 row=4'b1101;
		//#35 row=4'b1101;
		#20 row=4'b1111;
		#5 row=4'b1011;
		#20 row=4'b1111;
		#15 row=4'b1011;
		#50 row=4'b1111;
		#30 row=4'b1011;
		#20 row=4'b1111;
		#40 row=4'b1011;
		#20 row=4'b1111;
		#10 row=4'b0111;
		#5  row=4'b1111;
		#25 row=4'b0111;
		#30 row=4'b0111;
		#20 row=4'b1111;
		#30 row=4'b0111;
		#20 row=4'b1111;
		#40 row=4'b0111;
		#20 row=4'b1111;
		#10 row=4'b1110;
		#20 row=4'b1111;
		#20 row=4'b1110;
end
		always 
		#5 clock=~clock;
		initial#750 $finish;
		    
	      
endmodule

Project/keypad.vcd
$date
	Wed Jul  2 08:01:11 2014
$end

$version
	Synopsys VCS version A-2008.09
$end

$timescale
	10ps
$end

$comment Csum: 1 a9b49777303898e5 $end


$scope module keypad_test $end
$var reg 4 ! row [3:0] $end
$var reg 1 " clock $end
$var reg 1 # reset $end
$var wire 1 $ col [3] $end
$var wire 1 % col [2] $end
$var wire 1 & col [1] $end
$var wire 1 ' col [0] $end
$var wire 1 ( data [3] $end
$var wire 1 ) data [2] $end
$var wire 1 * data [1] $end
$var wire 1 + data [0] $end
$var wire 1 , v $end

$scope module uut $end
$var reg 4 - col [3:0] $end
$var reg 4 . data [3:0] $end
$var reg 1 / v $end
$var wire 4 ! row [3:0] $end
$var wire 1 " clock $end
$var wire 1 # reset $end
$var reg 3 0 state [2:0] $end
$var reg 3 1 next_state [2:0] $end
$var reg 4 2 store [3:0] $end
$upscope $end

$upscope $end

$enddefinitions $end

#0
$dumpvars
0"
x'
x&
x%
x$
x+
x*
x)
x(
0#
x/
x,
bxxxx -
bxxxx .
bxxx 1
b1111 !
b000 0
b1111 2
$end
#500
1"
b000 1
b0000 -
0$
0%
0&
0'
0/
0,
#1000
1#
b1110 !
0"
#1500
1"
b1110 2
#2000
0"
#2500
b1111 !
1"
b001 1
b1111 2
#3000
b1110 !
0"
#3500
1"
b000 1
b001 0
b1110 2
#4000
0"
#4500
1"
b101 1
b000 0
b1110 -
1$
1%
1&
1/
1,
b0000 .
0(
0)
0*
0+
#5000
b1111 !
0"
#5500
1"
b001 1
b101 0
b1111 2
0/
0,
bxxxx .
x(
x)
x*
x+
#6000
0"
#6500
1"
b001 0
#7000
0"
#7500
b1110 !
1"
b010 1
b1110 2
#8000
0"
#8500
1"
b101 1
b010 0
1/
1,
b0000 .
0(
0)
0*
0+
#9000
0"
#9500
b1111 !
1"
b101 0
b1111 2
b1101 -
0&
1'
b0001 .
1+
#10000
0"
#10500
1"
b001 1
0/
0,
#11000
0"
#11500
1"
b001 0
#12000
0"
#12500
1"
b010 1
#13000
b1110 !
0"
#13500
1"
b010 0
b1110 2
#14000
0"
#14500
1"
b101 1
1/
1,
#15000
0"
#15500
1"
b101 0
#16000
0"
#16500
1"
0/
0,
#17000
b1111 !
0"
#17500
b1101 !
1"
b1101 2
#18000
0"
#18500
1"
#19000
0"
#19500
1"
#20000
b1111 !
0"
#20500
1"
b1111 2
#21000
0"
#21500
b1101 !
1"
b001 1
b1101 2
#22000
0"
#22500
1"
b101 1
b001 0
#23000
0"
#23500
b1111 !
1"
b101 0
b1111 2
b1110 -
1&
0'
1/
1,
b0100 .
1)
0+
#24000
0"
#24500
1"
b001 1
0/
0,
#25000
0"
#25500
1"
b001 0
#26000
b1101 !
0"
#26500
1"
b010 1
b1101 2
#27000
0"
#27500
1"
b101 1
b010 0
1/
1,
#28000
0"
#28500
1"
b101 0
b1101 -
0&
1'
b0101 .
1+
#29000
0"
#29500
1"
0/
0,
#30000
b1111 !
0"
#30500
1"
b1111 2
#31000
0"
#31500
1"
b001 1
#32000
0"
#32500
1"
b001 0
#33000
0"
#33500
b1101 !
1"
b010 1
b1101 2
#34000
0"
#34500
1"
b101 1
b010 0
b1110 -
1&
0'
1/
1,
b0100 .
0+
#35000
0"
#35500
b1111 !
1"
b101 0
b1111 2
b1101 -
0&
1'
b0101 .
1+
#36000
b1011 !
0"
#36500
1"
b001 1
b1011 2
0/
0,
#37000
0"
#37500
1"
b101 1
b001 0
#38000
b1111 !
0"
#38500
1"
b101 0
b1111 2
b1110 -
1&
0'
1/
1,
b1000 .
1(
0)
0+
#39000
0"
#39500
b1011 !
1"
b001 1
b1011 2
0/
0,
#40000
0"
#40500
1"
b101 1
b001 0
#41000
0"
#41500
1"
b101 0
1/
1,
#42000
0"
#42500
1"
0/
0,
#43000
0"
#43500
1"
#44000
0"
#44500
b1111 !
1"
b1111 2
#45000
0"
#45500
1"
b001 1
#46000
0"
#46500
1"
b001 0
#47000
0"
#47500
b1011 !
1"
b010 1
b1011 2
#48000
0"
#48500
1"
b101 1
b010 0
1/
1,
#49000
0"
#49500
b1111 !
1"
b101 0
b1111 2
b1101 -
0&
1'
b1001 .
1+
#50000
0"
#50500
1"
b001 1
0/
0,
#51000
0"
#51500
1"
b001 0
#52000
0"
#52500
1"
b010 1
#53000
0"
#53500
b1011 !
1"
b010 0
b1011 2
#54000
0"
#54500
1"
b101 1
1/
1,
#55000
0"
#55500
b1111 !
1"
b101 0
b1111 2
#56000
0"
#56500
b0111 !
1"
b001 1
b0111 2
0/
0,
#57000
b1111 !
0"
#57500
1"
b101 1
b001 0
b1111 2
#58000
0"
#58500
1"
b010 1
b101 0
#59000
0"
#59500
b0111 !
1"
b001 1
b010 0
b0111 2
#60000
0"
#60500
1"
b101 1
b001 0
1/
1,
b1101 .
1)
#61000
0"
#61500
1"
b101 0
b1110 -
1&
0'
b1100 .
0+
#62000
0"
#62500
1"
0/
0,
#63000
0"
#63500
1"
#64000
0"
#64500
b1111 !
1"
b1111 2
#65000
0"
#65500
1"
b001 1
#66000
0"
#66500
1"
b001 0
#67000
0"
#67500
b0111 !
1"
b010 1
b0111 2
#68000
0"
#68500
1"
b101 1
b010 0
1/
1,
#69000
0"
#69500
b1111 !
1"
b101 0
b1111 2
b1101 -
0&
1'
b1101 .
1+
#70000
0"
#70500
1"
b001 1
0/
0,
#71000
0"
#71500
1"
b001 0
#72000
0"
#72500
1"
b010 1
#73000
0"
#73500
b0111 !
1"
b010 0
b0111 2
#74000
0"
#74500
1"
b101 1
1/
1,
